snowglobe/sdk/__init__.py
snowglobe/sdk/client.py
snowglobe/sdk/errors.py
snowglobe/sdk/py.typed
snowglobe/sdk/types.py
snowglobe/sdk/api/__init__.py
snowglobe/sdk/api/default/__init__.py
snowglobe/sdk/api/default/delete_api_agents_id.py
snowglobe/sdk/api/default/delete_api_simulations_id.py
snowglobe/sdk/api/default/get_api_agents_id.py
snowglobe/sdk/api/default/get_api_applications_id.py
snowglobe/sdk/api/default/get_api_experiments_id.py
snowglobe/sdk/api/default/get_api_experiments_id_download_data.py
snowglobe/sdk/api/default/get_api_experiments_id_tests_test_id.py
snowglobe/sdk/api/default/get_api_experiments_id_tests_test_id_conversations.py
snowglobe/sdk/api/default/get_api_risks_id.py
snowglobe/sdk/api/default/get_api_simulations_id.py
snowglobe/sdk/api/default/get_api_simulations_id_download_data.py
snowglobe/sdk/api/default/patch_api_agents_id.py
snowglobe/sdk/api/default/patch_api_simulations_id.py
snowglobe/sdk/api/default/post_api_agents.py
snowglobe/sdk/api/default/post_api_applications.py
snowglobe/sdk/api/default/post_api_batch_experiments_id_tests_test_id_evaluations.py
snowglobe/sdk/api/default/post_api_experiments.py
snowglobe/sdk/api/default/post_api_simulations.py
snowglobe/sdk/api/default/put_api_documents_upload.py
snowglobe/sdk/api/default/put_api_experiments_id_settings.py
snowglobe/sdk/api/default/put_api_simulations_id_settings.py
snowglobe/sdk/models/__init__.py
snowglobe/sdk/models/agent.py
snowglobe/sdk/models/agent_autofix_configuration_type_0.py
snowglobe/sdk/models/agent_connection_info_type_0.py
snowglobe/sdk/models/agent_connection_info_type_0_extra_body_item.py
snowglobe/sdk/models/agent_connection_info_type_0_extra_headers_item.py
snowglobe/sdk/models/agent_create_schema.py
snowglobe/sdk/models/agent_create_schema_connection_info_type_0.py
snowglobe/sdk/models/agent_create_schema_connection_info_type_0_extra_body_item.py
snowglobe/sdk/models/agent_create_schema_connection_info_type_0_extra_headers_item.py
snowglobe_sdk-0.2.6.dist-info/licenses/LICENSE
snowglobe_sdk-0.2.6.dist-info/METADATA
snowglobe_sdk-0.2.6.dist-info/WHEEL
snowglobe_sdk-0.2.6.dist-info/top_level.txt
snowglobe_sdk-0.2.6.dist-info/RECORD
