Metadata-Version: 2.4
Name: snowglobe-sdk
Version: 0.2.6
Summary: A client library for accessing Snowglobe SDK
Author: Guardrails AI
Author-email: contact@guardrailsai.com
Classifier: Programming Language :: Python :: 3
Requires-Python: >=3.9, <4
License-File: LICENSE
Requires-Dist: httpx<0.29.0,>=0.23.0
Requires-Dist: attrs>=22.2.0
Requires-Dist: python-dateutil<3,>=2.8.0
Provides-Extra: dev
Requires-Dist: pytest>=7.2.1; extra == "dev"
Requires-Dist: pytest-cov>=2.8.1; extra == "dev"
Requires-Dist: tox>=3.9.0; extra == "dev"
Requires-Dist: flake8>=4.0.0; extra == "dev"
Requires-Dist: types-python-dateutil>=2.8.19.14; extra == "dev"
Requires-Dist: mypy>=1.5; extra == "dev"
Requires-Dist: ruff<0.2.0,>=0.1.0; extra == "dev"
Dynamic: description
Dynamic: description-content-type
Dynamic: license-file
Dynamic: requires-dist
Dynamic: requires-python
Dynamic: summary
